README.md
setup.py
svautil/__init__.py
svautil/vna.py
svautil.egg-info/PKG-INFO
svautil.egg-info/SOURCES.txt
svautil.egg-info/dependency_links.txt
svautil.egg-info/not-zip-safe
svautil.egg-info/requires.txt
svautil.egg-info/top_level.txt