Metadata-Version: 1.0
Name: svautil
Version: 0.0.3
Summary: Converts CSV files from Sigilent Vector Spectrum Analyzers to a Scikit RF network.
Home-page: https://github.com/norsk-datateknikk/SVA-Utility
Author: Erik Buer
Author-email: erik.buer@norskdatateknikk.no
License: GPL
Platform: UNKNOWN
